{
  "id": "geography_trivia_26k_39",
  "name": "Geography Trivia 26K 39",
  "description": "Geography 1901 - 1950 from Anki Trivia 26k.",
  "author": "ricardofig016",
  "language": "us",
  "tags": [
    "trivia",
    "geography"
  ],
  "items": [
    {
      "id": "geography_trivia_26k_39_01",
      "title": "Which former Soviet Republic has Tashkent as its capital?",
      "answers": [
        "Uzbekistan"
      ],
      "mnemonic": "",
      "notes": ""
    },
    {
      "id": "geography_trivia_26k_39_02",
      "title": "What desert is home to the Ahaggar and Tibesti mountains?",
      "answers": [
        "Sahara"
      ],
      "mnemonic": "",
      "notes": ""
    },
    {
      "id": "geography_trivia_26k_39_03",
      "title": "Lake Sakakawea is the largest lake in which US state?",
      "answers": [
        "North Dakota"
      ],
      "mnemonic": "",
      "notes": ""
    },
    {
      "id": "geography_trivia_26k_39_04",
      "title": "Paramaribo is the capital of which country?",
      "answers": [
        "Suriname"
      ],
      "mnemonic": "",
      "notes": ""
    },
    {
      "id": "geography_trivia_26k_39_05",
      "title": "Which East Asian country celebrates Golden Week?",
      "answers": [
        "Japan"
      ],
      "mnemonic": "",
      "notes": ""
    },
    {
      "id": "geography_trivia_26k_39_06",
      "title": "Where's the famed Arch of Hadrian?",
      "answers": [
        "Athens"
      ],
      "mnemonic": "",
      "notes": ""
    },
    {
      "id": "geography_trivia_26k_39_07",
      "title": "Which US coast is the state of Maryland located on?",
      "answers": [
        "East"
      ],
      "mnemonic": "",
      "notes": ""
    },
    {
      "id": "geography_trivia_26k_39_08",
      "title": "What is the Napa Valley best known for?",
      "answers": [
        "Wine"
      ],
      "mnemonic": "",
      "notes": ""
    },
    {
      "id": "geography_trivia_26k_39_09",
      "title": "The Canadian city of Windsor is linked to what US city by the Ambassador Bridge?",
      "answers": [
        "Detroit"
      ],
      "mnemonic": "",
      "notes": ""
    },
    {
      "id": "geography_trivia_26k_39_10",
      "title": "What strait connects the Persian Gulf to the Gulf of Oman?",
      "answers": [
        "Strait of Hormuz"
      ],
      "mnemonic": "",
      "notes": ""
    },
    {
      "id": "geography_trivia_26k_39_11",
      "title": "What US territory includes the islands of Saint Croix, Saint John and Saint Thomas?",
      "answers": [
        "US Virgin Islands"
      ],
      "mnemonic": "",
      "notes": ""
    },
    {
      "id": "geography_trivia_26k_39_12",
      "title": "Mount hotham is located in which country?",
      "answers": [
        "Australia"
      ],
      "mnemonic": "",
      "notes": ""
    },
    {
      "id": "geography_trivia_26k_39_13",
      "title": "Which is the driest, non-polar desert on Earth?",
      "answers": [
        "Atacama Desert"
      ],
      "mnemonic": "",
      "notes": ""
    },
    {
      "id": "geography_trivia_26k_39_14",
      "title": "Which continent is home to the only egg-laying mammals in the world?",
      "answers": [
        "Australia"
      ],
      "mnemonic": "",
      "notes": ""
    },
    {
      "id": "geography_trivia_26k_39_15",
      "title": "Which African country had its capital transferred to Abuja?",
      "answers": [
        "Nigeria"
      ],
      "mnemonic": "",
      "notes": ""
    },
    {
      "id": "geography_trivia_26k_39_16",
      "title": "As of 2020, which European country got about 3/4 of its electricity from nuclear power, the most of any country?",
      "answers": [
        "France"
      ],
      "mnemonic": "",
      "notes": ""
    },
    {
      "id": "geography_trivia_26k_39_17",
      "title": "On which coast would you find the smallest Canadian province?",
      "answers": [
        "East coast"
      ],
      "mnemonic": "",
      "notes": ""
    },
    {
      "id": "geography_trivia_26k_39_18",
      "title": "What is the capital of Poland?",
      "answers": [
        "Warsaw"
      ],
      "mnemonic": "",
      "notes": ""
    },
    {
      "id": "geography_trivia_26k_39_19",
      "title": "What is Lynchburg, Tennessee famous for?",
      "answers": [
        "Jack Daniels whiskey"
      ],
      "mnemonic": "",
      "notes": ""
    },
    {
      "id": "geography_trivia_26k_39_20",
      "title": "What location was used to film the movie \"Jaws\"?",
      "answers": [
        "Martha’s Vineyard, Massachusetts"
      ],
      "mnemonic": "",
      "notes": ""
    },
    {
      "id": "geography_trivia_26k_39_21",
      "title": "In what country was the concentration camp \"Treblinka\" located?",
      "answers": [
        "Poland"
      ],
      "mnemonic": "",
      "notes": ""
    },
    {
      "id": "geography_trivia_26k_39_22",
      "title": "What country would you find Mount Elbrus in?",
      "answers": [
        "Russia"
      ],
      "mnemonic": "",
      "notes": ""
    },
    {
      "id": "geography_trivia_26k_39_23",
      "title": "Before being renamed, what was Mumbai called?",
      "answers": [
        "Bombay"
      ],
      "mnemonic": "",
      "notes": ""
    },
    {
      "id": "geography_trivia_26k_39_24",
      "title": "In what country would you find the mouths of the river Nile?",
      "answers": [
        "Egypt"
      ],
      "mnemonic": "",
      "notes": ""
    },
    {
      "id": "geography_trivia_26k_39_25",
      "title": "The Hunua Ranges is located where?",
      "answers": [
        "New Zealand"
      ],
      "mnemonic": "",
      "notes": ""
    },
    {
      "id": "geography_trivia_26k_39_26",
      "title": "The city of Machu Picchu is located in which country?",
      "answers": [
        "Peru"
      ],
      "mnemonic": "",
      "notes": ""
    },
    {
      "id": "geography_trivia_26k_39_27",
      "title": "What is the smallest Canadian province?",
      "answers": [
        "Prince Edward Island"
      ],
      "mnemonic": "",
      "notes": ""
    },
    {
      "id": "geography_trivia_26k_39_28",
      "title": "In which US state is Crater Lake found?",
      "answers": [
        "Oregon"
      ],
      "mnemonic": "",
      "notes": ""
    },
    {
      "id": "geography_trivia_26k_39_29",
      "title": "What country was the modern bicycle invented in?",
      "answers": [
        "Germany"
      ],
      "mnemonic": "",
      "notes": ""
    },
    {
      "id": "geography_trivia_26k_39_30",
      "title": "Which city is home to the South-of-Market district?",
      "answers": [
        "San Francisco"
      ],
      "mnemonic": "",
      "notes": ""
    },
    {
      "id": "geography_trivia_26k_39_31",
      "title": "Christmas Island is a territory belonging to which country?",
      "answers": [
        "Australia"
      ],
      "mnemonic": "",
      "notes": ""
    },
    {
      "id": "geography_trivia_26k_39_32",
      "title": "The Plains of Abraham is in which Canadian province?",
      "answers": [
        "Quebec"
      ],
      "mnemonic": "",
      "notes": ""
    },
    {
      "id": "geography_trivia_26k_39_33",
      "title": "What mountain range stretches from the town of Seesen in northwest Germany to Eisleben in the east?",
      "answers": [
        "Harz"
      ],
      "mnemonic": "",
      "notes": ""
    },
    {
      "id": "geography_trivia_26k_39_34",
      "title": "Death Valley is located in which US state?",
      "answers": [
        "California"
      ],
      "mnemonic": "",
      "notes": ""
    },
    {
      "id": "geography_trivia_26k_39_35",
      "title": "What is the world's largest island?",
      "answers": [
        "Greenland"
      ],
      "mnemonic": "",
      "notes": ""
    },
    {
      "id": "geography_trivia_26k_39_36",
      "title": "Which New England state does not have any ocean coastline?",
      "answers": [
        "Vermont"
      ],
      "mnemonic": "",
      "notes": ""
    },
    {
      "id": "geography_trivia_26k_39_37",
      "title": "Mogadishu is the capital of which African country?",
      "answers": [
        "Somalia"
      ],
      "mnemonic": "",
      "notes": ""
    },
    {
      "id": "geography_trivia_26k_39_38",
      "title": "What Atlantic island getaway are you visiting if you're staying in the capital city of Hamilton?",
      "answers": [
        "Bermuda"
      ],
      "mnemonic": "",
      "notes": ""
    },
    {
      "id": "geography_trivia_26k_39_39",
      "title": "On which US river is the Grand Coulee Dam?",
      "answers": [
        "Columbia"
      ],
      "mnemonic": "",
      "notes": ""
    },
    {
      "id": "geography_trivia_26k_39_40",
      "title": "Which U.S. Interstate highway is the longest?",
      "answers": [
        "I-90"
      ],
      "mnemonic": "",
      "notes": ""
    },
    {
      "id": "geography_trivia_26k_39_41",
      "title": "Which US state is nicknamed the \"Keystone State\"?",
      "answers": [
        "Pennsylvania"
      ],
      "mnemonic": "",
      "notes": ""
    },
    {
      "id": "geography_trivia_26k_39_42",
      "title": "What is the capital of Catalonia?",
      "answers": [
        "Barcelona"
      ],
      "mnemonic": "",
      "notes": ""
    },
    {
      "id": "geography_trivia_26k_39_43",
      "title": "The Atomium is a famous tourist attraction in which city?",
      "answers": [
        "Brussels"
      ],
      "mnemonic": "",
      "notes": ""
    },
    {
      "id": "geography_trivia_26k_39_44",
      "title": "Off what country lies the island of Zanzibar?",
      "answers": [
        "Tanzania"
      ],
      "mnemonic": "",
      "notes": ""
    },
    {
      "id": "geography_trivia_26k_39_45",
      "title": "How many Brazilian states are there?",
      "answers": [
        "26"
      ],
      "mnemonic": "",
      "notes": ""
    },
    {
      "id": "geography_trivia_26k_39_46",
      "title": "What islands were purchased by the US from Denmark in 1916?",
      "answers": [
        "US Virgin Islands"
      ],
      "mnemonic": "",
      "notes": ""
    },
    {
      "id": "geography_trivia_26k_39_47",
      "title": "In which US state is Shenandoah National Park located?",
      "answers": [
        "Virginia"
      ],
      "mnemonic": "",
      "notes": ""
    },
    {
      "id": "geography_trivia_26k_39_48",
      "title": "What country is the \"land of the lions\"?",
      "answers": [
        "Singapore"
      ],
      "mnemonic": "",
      "notes": ""
    },
    {
      "id": "geography_trivia_26k_39_49",
      "title": "Which country's capital city lies on the River Aar?",
      "answers": [
        "Switzerland"
      ],
      "mnemonic": "",
      "notes": ""
    },
    {
      "id": "geography_trivia_26k_39_50",
      "title": "In which South American country is the Atacama desert?",
      "answers": [
        "Chile"
      ],
      "mnemonic": "",
      "notes": ""
    }
  ]
}