{
  "id": "science_trivia_26k_46",
  "name": "Science Trivia 26K 46",
  "description": "Science 2251 - 2300 from Anki Trivia 26k.",
  "author": "ricardofig016",
  "language": "us",
  "tags": [
    "trivia",
    "science"
  ],
  "items": [
    {
      "id": "science_trivia_26k_46_01",
      "title": "Which media is read from the outside in, compact discs or vinyl records?",
      "answers": [
        "Vinyl records"
      ],
      "mnemonic": "",
      "notes": ""
    },
    {
      "id": "science_trivia_26k_46_02",
      "title": "Nuclear membrane, cytoplasm, and nucleus are parts of a what?",
      "answers": [
        "Cell"
      ],
      "mnemonic": "",
      "notes": ""
    },
    {
      "id": "science_trivia_26k_46_03",
      "title": "The \"Wandering\" species of what bird has the longest wingspan in nature?",
      "answers": [
        "Albatross"
      ],
      "mnemonic": "",
      "notes": ""
    },
    {
      "id": "science_trivia_26k_46_04",
      "title": "What structure in the back of the brain governs motor control?",
      "answers": [
        "Cerebellum"
      ],
      "mnemonic": "",
      "notes": ""
    },
    {
      "id": "science_trivia_26k_46_05",
      "title": "How many scents can the human nose detect?",
      "answers": [
        "More than 1 Trillion"
      ],
      "mnemonic": "",
      "notes": ""
    },
    {
      "id": "science_trivia_26k_46_06",
      "title": "A nilometer measures the level of what?",
      "answers": [
        "The river Nile"
      ],
      "mnemonic": "",
      "notes": ""
    },
    {
      "id": "science_trivia_26k_46_07",
      "title": "What are there 270 of in the average human baby but only 206 in an adult?",
      "answers": [
        "Bones"
      ],
      "mnemonic": "",
      "notes": ""
    },
    {
      "id": "science_trivia_26k_46_08",
      "title": "What scientist's book laid the foundations for classical mechanics?",
      "answers": [
        "Isaac Newton"
      ],
      "mnemonic": "",
      "notes": ""
    },
    {
      "id": "science_trivia_26k_46_09",
      "title": "What is the name of the part of your back you cannot reach?",
      "answers": [
        "Acnestis"
      ],
      "mnemonic": "",
      "notes": ""
    },
    {
      "id": "science_trivia_26k_46_10",
      "title": "What is the name for the sun's outer atmosphere?",
      "answers": [
        "The corona"
      ],
      "mnemonic": "",
      "notes": ""
    },
    {
      "id": "science_trivia_26k_46_11",
      "title": "What precious stones were originally used to polish axes in the Stone Age?",
      "answers": [
        "Diamonds"
      ],
      "mnemonic": "",
      "notes": ""
    },
    {
      "id": "science_trivia_26k_46_12",
      "title": "What type of creature is an Orb Weaver?",
      "answers": [
        "Spider"
      ],
      "mnemonic": "",
      "notes": ""
    },
    {
      "id": "science_trivia_26k_46_13",
      "title": "Which Russian chemist created the modern periodic table?",
      "answers": [
        "Dmitri Mendeleev"
      ],
      "mnemonic": "",
      "notes": ""
    },
    {
      "id": "science_trivia_26k_46_14",
      "title": "What is the name of the bony covering over the gills of ray-finned fishes?",
      "answers": [
        "Operculum"
      ],
      "mnemonic": "",
      "notes": ""
    },
    {
      "id": "science_trivia_26k_46_15",
      "title": "What element has the atomic number 26?",
      "answers": [
        "Iron"
      ],
      "mnemonic": "",
      "notes": ""
    },
    {
      "id": "science_trivia_26k_46_16",
      "title": "What is the chemical formula for table salt?",
      "answers": [
        "NaCl"
      ],
      "mnemonic": "",
      "notes": ""
    },
    {
      "id": "science_trivia_26k_46_17",
      "title": "How many times is a Roman numeral’s value increased if it has a line over it?",
      "answers": [
        "1,000"
      ],
      "mnemonic": "",
      "notes": ""
    },
    {
      "id": "science_trivia_26k_46_18",
      "title": "What do male lions do about 20 hours a day?",
      "answers": [
        "Sleep"
      ],
      "mnemonic": "",
      "notes": ""
    },
    {
      "id": "science_trivia_26k_46_19",
      "title": "What element has the periodic table name Sb?",
      "answers": [
        "Antimony"
      ],
      "mnemonic": "",
      "notes": ""
    },
    {
      "id": "science_trivia_26k_46_20",
      "title": "When a nose is said to be \"Retrousse\", what does it mean?",
      "answers": [
        "It turns upward"
      ],
      "mnemonic": "",
      "notes": ""
    },
    {
      "id": "science_trivia_26k_46_21",
      "title": "Honeydew is a variety of what?",
      "answers": [
        "Melon"
      ],
      "mnemonic": "",
      "notes": ""
    },
    {
      "id": "science_trivia_26k_46_22",
      "title": "Which mosquito bites humans, male or female?",
      "answers": [
        "Female"
      ],
      "mnemonic": "",
      "notes": ""
    },
    {
      "id": "science_trivia_26k_46_23",
      "title": "What fiber-producing plant is attacked by the boll weevil?",
      "answers": [
        "Cotton"
      ],
      "mnemonic": "",
      "notes": ""
    },
    {
      "id": "science_trivia_26k_46_24",
      "title": "What is a \"Blenheim Orange\"?",
      "answers": [
        "Apple"
      ],
      "mnemonic": "",
      "notes": ""
    },
    {
      "id": "science_trivia_26k_46_25",
      "title": "What disease is the focus of oncology?",
      "answers": [
        "Cancer"
      ],
      "mnemonic": "",
      "notes": ""
    },
    {
      "id": "science_trivia_26k_46_26",
      "title": "What kind of muscle contraction is also referred to as \"static tension\"?",
      "answers": [
        "Isometric"
      ],
      "mnemonic": "",
      "notes": ""
    },
    {
      "id": "science_trivia_26k_46_27",
      "title": "What is the carambola fruit more commonly referred to as?",
      "answers": [
        "Starfruit"
      ],
      "mnemonic": "",
      "notes": ""
    },
    {
      "id": "science_trivia_26k_46_28",
      "title": "What is the more common name for Tympanum?",
      "answers": [
        "Eardrum"
      ],
      "mnemonic": "",
      "notes": ""
    },
    {
      "id": "science_trivia_26k_46_29",
      "title": "Who is \"the Science Guy\"?",
      "answers": [
        "Bill Nye"
      ],
      "mnemonic": "",
      "notes": ""
    },
    {
      "id": "science_trivia_26k_46_30",
      "title": "What name is given to shellfish that cling to the bottom of ships?",
      "answers": [
        "Barnacles"
      ],
      "mnemonic": "",
      "notes": ""
    },
    {
      "id": "science_trivia_26k_46_31",
      "title": "Why do snails produce slime?",
      "answers": [
        "To stick to surfaces"
      ],
      "mnemonic": "",
      "notes": ""
    },
    {
      "id": "science_trivia_26k_46_32",
      "title": "Which English sci-fi writer first conceived the idea of artificial communication satellites in 1945?",
      "answers": [
        "Arthur C. Clarke"
      ],
      "mnemonic": "",
      "notes": ""
    },
    {
      "id": "science_trivia_26k_46_33",
      "title": "What is the explosion at the end of a star's life cycle called?",
      "answers": [
        "Supernova"
      ],
      "mnemonic": "",
      "notes": ""
    },
    {
      "id": "science_trivia_26k_46_34",
      "title": "What is the axilla better known as?",
      "answers": [
        "Armpit"
      ],
      "mnemonic": "",
      "notes": ""
    },
    {
      "id": "science_trivia_26k_46_35",
      "title": "What material is produced from the gossypium shrub?",
      "answers": [
        "Cotton"
      ],
      "mnemonic": "",
      "notes": ""
    },
    {
      "id": "science_trivia_26k_46_36",
      "title": "What sensory organ do starfish have at the end of each arm?",
      "answers": [
        "Eye"
      ],
      "mnemonic": "",
      "notes": ""
    },
    {
      "id": "science_trivia_26k_46_37",
      "title": "Scolionophobia is the fear of what?",
      "answers": [
        "School"
      ],
      "mnemonic": "",
      "notes": ""
    },
    {
      "id": "science_trivia_26k_46_38",
      "title": "What ape's name is Malay for \"old man of the forest\"?",
      "answers": [
        "The orangutan's"
      ],
      "mnemonic": "",
      "notes": ""
    },
    {
      "id": "science_trivia_26k_46_39",
      "title": "How many colors are there in a rainbow?",
      "answers": [
        "Seven"
      ],
      "mnemonic": "",
      "notes": ""
    },
    {
      "id": "science_trivia_26k_46_40",
      "title": "What does \"holistic\" mean in reference to holistic medicine?",
      "answers": [
        "Addressing the whole person"
      ],
      "mnemonic": "",
      "notes": ""
    },
    {
      "id": "science_trivia_26k_46_41",
      "title": "Gunpowder, paper, and soy sauce were all invented in what country?",
      "answers": [
        "China"
      ],
      "mnemonic": "",
      "notes": ""
    },
    {
      "id": "science_trivia_26k_46_42",
      "title": "What element has the chemical symbol K?",
      "answers": [
        "Potassium"
      ],
      "mnemonic": "",
      "notes": ""
    },
    {
      "id": "science_trivia_26k_46_43",
      "title": "How much of the daily recommended calcium intake does a glass of milk contain?",
      "answers": [
        "39%"
      ],
      "mnemonic": "",
      "notes": ""
    },
    {
      "id": "science_trivia_26k_46_44",
      "title": "What term for an adult male gorilla comes from a distinctive patch of hair?",
      "answers": [
        "Silverback"
      ],
      "mnemonic": "",
      "notes": ""
    },
    {
      "id": "science_trivia_26k_46_45",
      "title": "What is the correct term for a group of whales?",
      "answers": [
        "Pod"
      ],
      "mnemonic": "",
      "notes": ""
    },
    {
      "id": "science_trivia_26k_46_46",
      "title": "What is the scientific name for the job or role an organism plays in its habitat?",
      "answers": [
        "Niche"
      ],
      "mnemonic": "",
      "notes": ""
    },
    {
      "id": "science_trivia_26k_46_47",
      "title": "What dictates whether a sea turtle is male or female?",
      "answers": [
        "Incubation temperature"
      ],
      "mnemonic": "",
      "notes": ""
    },
    {
      "id": "science_trivia_26k_46_48",
      "title": "What is a plant with no internal system of tube like structures called?",
      "answers": [
        "Nonvascular Plant"
      ],
      "mnemonic": "",
      "notes": ""
    },
    {
      "id": "science_trivia_26k_46_49",
      "title": "The conversion of ethanol to ethanoic acid is an example of what?",
      "answers": [
        "Oxidation"
      ],
      "mnemonic": "",
      "notes": ""
    },
    {
      "id": "science_trivia_26k_46_50",
      "title": "What is the name of the point of no return around the edge of a black hole?",
      "answers": [
        "Event horizon"
      ],
      "mnemonic": "",
      "notes": ""
    }
  ]
}